dagster_unity_catalog_polars/__init__.py
dagster_unity_catalog_polars/debug_unity_catalog_iomanager.py
dagster_unity_catalog_polars/unity_catalog_iomanager.py
dagster_unity_catalog_polars/utils.py
dagster_unity_catalog_polars-0.2.2.dist-info/METADATA
dagster_unity_catalog_polars-0.2.2.dist-info/WHEEL
dagster_unity_catalog_polars-0.2.2.dist-info/licenses/LICENSE
dagster_unity_catalog_polars-0.2.2.dist-info/RECORD
