Metadata-Version: 2.4
Name: dagster-unity-catalog-polars
Version: 0.2.2
Summary: Polars Unity Catalog IO Managers for Dagster
Author-email: Gian Violi <96206151+gfvioli@users.noreply.github.com>, Ion Koutsouris <15728914+ion-elgreco@users.noreply.github.com>, Stefan Verbruggen <27513235+sverbruggen@users.noreply.github.com>
License: 
License-File: LICENSE
Keywords: dagster,databricks,io manager,polars,unity catalog
Classifier: License :: OSI Approved :: Apache Software License
Classifier: Programming Language :: Python :: 3.9
Classifier: Programming Language :: Python :: 3.10
Classifier: Programming Language :: Python :: 3.11
Classifier: Programming Language :: Python :: 3.12
Requires-Python: >=3.9
Requires-Dist: dagster>=1.11
Requires-Dist: databricks-sdk>=0.40.0
Requires-Dist: databricks-sql-connector>=4.0.0
Requires-Dist: polars>=1.30
Requires-Dist: pydantic>=2.9.2
